richterm/__init__.py
richterm/__main__.py
richterm/_core.py
richterm/py.typed
richterm/sphinxext.py
richterm-0.2.0.dist-info/licenses/LICENSE
richterm-0.2.0.dist-info/WHEEL
richterm-0.2.0.dist-info/entry_points.txt
richterm-0.2.0.dist-info/METADATA
richterm-0.2.0.dist-info/RECORD
