Metadata-Version: 2.4
Name: richterm
Version: 0.2.0
Summary: Generate colorful screenshots of terminal commands
Keywords: 
Author: Martín Gaitán
Author-email: Martín Gaitán <gaitan@gmail.com>
License-Expression: BSD-3-Clause
License-File: LICENSE
Classifier: Development Status :: 4 - Beta
Classifier: Intended Audience :: Developers
Classifier: Programming Language :: Python
Classifier: Programming Language :: Python :: 3
Classifier: Programming Language :: Python :: 3 :: Only
Classifier: Programming Language :: Python :: 3.11
Classifier: Programming Language :: Python :: 3.12
Classifier: Programming Language :: Python :: 3.13
Classifier: Programming Language :: Python :: 3.14
Classifier: Topic :: Documentation
Classifier: Topic :: Software Development
Classifier: Topic :: Utilities
Classifier: Typing :: Typed
Requires-Dist: rich
Requires-Dist: sphinx>=7.4.7 ; extra == 'sphinx'
Requires-Dist: myst-parser>=3.0.0 ; extra == 'sphinx'
Requires-Python: >=3.11
Project-URL: Changelog, https://github.com/mgaitan/richterm/releases
Project-URL: Documentation, https://mgaitan.github.io/richterm
Project-URL: Funding, https://github.com/sponsors/mgaitan
Project-URL: Homepage, https://mgaitan.github.io/richterm
Project-URL: Issues, https://github.com/mgaitan/richterm/issues
Project-URL: Repository, https://github.com/mgaitan/richterm
Provides-Extra: sphinx
